pyhaproxy/__init__.py
pyhaproxy/config.py
pyhaproxy/haproxy.peg
pyhaproxy/parse.py
pyhaproxy/pegnode.py
pyhaproxy/render.py
pyhaproxy/test.py
pyhaproxy-0.3.6.dist-info/DESCRIPTION.rst
pyhaproxy-0.3.6.dist-info/METADATA
pyhaproxy-0.3.6.dist-info/RECORD
pyhaproxy-0.3.6.dist-info/WHEEL
pyhaproxy-0.3.6.dist-info/metadata.json
pyhaproxy-0.3.6.dist-info/top_level.txt
