Metadata-Version: 2.0
Name: pyhaproxy
Version: 0.3.6
Summary: A Python library to parse haproxy configuration file
Home-page: https://github.com/imjoey/pyhaproxy
Author: Joey
Author-email: majunjiev@gmail.com
License: MIT License
Keywords: haproxy,parse
Platform: any
